{
  "site": {
    "title": "Katy Saintin",
    "url": "https://katysaintin.github.io",
    "author": "Katy Saintin",
    "defaultLanguage": "fr"
  },
  "analytics": {
    "googleAnalyticsId": "GTM-T7D5VSDZ"
  },
  "theme": {
    "primary": "#2f3b73",
    "secondary": "#c96f4a",
    "background": "#f8f7f4",
    "text": "#202020"
  },
  "hero": {
    "fr": {
      "name": "Katy Saintin",
      "title": "Experte Senior CEA",
      "subtitle": "Scientific Software & Data Engineering",
      "keywords": [
        "SCADA",
        "EPICS",
        "TANGO",
        "Scientific Data",
        "IA"
      ]
    },
    "en": {
      "name": "Katy Saintin",
      "title": "CEA Senior Expert",
      "subtitle": "Scientific Software & Data Engineering",
      "keywords": [
        "SCADA",
        "EPICS",
        "TANGO",
        "Scientific Data",
        "AI"
      ]
    }
  },
  "stats": [
    {
      "value": "25+",
      "fr": "Années d'expérience",
      "en": "Years Experience"
    },
    {
      "value": "20+",
      "fr": "Publications internationales",
      "en": "International Publications"
    },
    {
      "value": "40+",
      "fr": "Projets MUSCADE",
      "en": "MUSCADE Projects"
    },
    {
      "value": "90+",
      "fr": "Systèmes supportés",
      "en": "Systems Supported"
    }
  ],
  "featured": [
    {
      "emoji": "📄",
      "titleFr": "Curriculum Vitae",
      "titleEn": "Curriculum Vitae",
      "descriptionFr": "Experte Senior CEA • Scientific Software & Data Engineering",
      "descriptionEn": "CEA Senior Expert • Scientific Software & Data Engineering",
      "url": "cv.html"
    }
  ],
  "achievements": [
    {
      "fr": "Créatrice du SOLEIL DataBrowser",
      "en": "Creator of SOLEIL DataBrowser"
    },
    {
      "fr": "Créatrice du Scientific Data Retriever (SDR)",
      "en": "Creator of Scientific Data Retriever (SDR)"
    },
    {
      "fr": "Responsable produit MUSCADE",
      "en": "MUSCADE Product Owner"
    },
    {
      "fr": "Experte Senior CEA",
      "en": "CEA Senior Expert"
    },
    {
      "fr": "Conférencière internationale depuis plus de 20 ans",
      "en": "International Conference Speaker for 20+ years"
    }
  ],
  "universes": [
    {
      "emoji": "⚙️",
      "title": "Katy In Control",
      "descriptionFr": "SCADA, EPICS, TANGO et contrôle-commande scientifique",
      "descriptionEn": "SCADA, EPICS, TANGO and scientific control systems",
      "url": "https://github.com/katysaintin/KatyInControl"
    },
    {
      "emoji": "🎓",
      "title": "Hors Kadre",
      "descriptionFr": "Orientation, Parcoursup et accompagnement des familles",
      "descriptionEn": "Student orientation and higher education guidance",
      "url": "https://horskadre.github.io"
    },
    {
      "emoji": "✍️",
      "title": "Medium",
      "descriptionFr": "Articles techniques et retours d'expérience",
      "descriptionEn": "Technical articles and experience sharing",
      "url": "https://medium.com/@katy.saintin"
    },
    {
      "emoji": "🎙️",
      "title": "Podcast",
      "descriptionFr": "Vulgarisation scientifique et technique",
      "descriptionEn": "Scientific and technical outreach",
      "url": ""
    },
    {
      "emoji": "📸",
      "title": "Photography",
      "descriptionFr": "Fashion, portraits et publications internationales",
      "descriptionEn": "Fashion, portraits and international publications",
      "url": ""
    },
    {
      "emoji": "🎵",
      "title": "Music",
      "descriptionFr": "Composition, chant et concerts",
      "descriptionEn": "Music composition, vocals and live performances",
      "url": ""
    }
  ],
  "menu": [
    {
      "emoji": "🏠",
      "fr": "Accueil",
      "en": "Home",
      "url": "index.html"
    },
    {
      "emoji": "📄",
      "fr": "CV",
      "en": "CV",
      "url": "cv.html"
    },
    {
      "emoji": "💻",
      "fr": "Portfolio",
      "en": "Portfolio",
      "url": "portfolio.html"
    },
    {
      "emoji": "📚",
      "fr": "Publications",
      "en": "Publications",
      "url": "cv.html#publications"
    },
    {
      "emoji": "🎤",
      "fr": "Conférences",
      "en": "Conferences",
      "url": "cv.html#talks"
    },
    {
      "emoji": "🎓",
      "fr": "Enseignement",
      "en": "Teaching",
      "url": "teaching.html"
    },
    {
      "emoji": "⚙️",
      "fr": "Katy In Control",
      "en": "Katy In Control",
      "url": "community.html"
    },
    {
      "emoji": "🧠",
      "fr": "IA & Digital Twin",
      "en": "AI & Digital Twin",
      "url": "ai.html"
    }
  ],
  "footer": {
    "email": "",
    "linkedin": "",
    "github": "https://github.com/katysaintin",
    "copyright": "© Katy Saintin"
  }
}
